{
  "commercial_id": "tv_com_1980_46",
  "status": "success",
  "source_dir": "corpus/05_frames/tv_com_1980_46",
  "source_manifest": "corpus/05_frames/tv_com_1980_46/frames_manifest.json",
  "source_manifest_available": true,
  "output_dir": "corpus/05_frames_selected/tv_com_1980_46",
  "selection_config": {
    "exclude_dark_frames": true,
    "dark_pixel_threshold": 30.0,
    "max_mean_luminance_for_dark": 35.0,
    "max_median_luminance_for_dark": 30.0,
    "min_dark_pixel_ratio_for_dark": 0.85,
    "deduplicate_frames": true,
    "duplicate_distance_threshold": 0.035,
    "dedup_signature_size": 32,
    "dedup_lookback": 1,
    "allow_fallback_frame": true
  },
  "input_frame_count": 117,
  "dark_rejected_count": 27,
  "duplicate_rejected_count": 19,
  "selected_frame_count": 71,
  "fallback_used": false,
  "frames": [
    {
      "frame_index": 1,
      "filename": "frame_0001.jpg",
      "path": "corpus/05_frames_selected/tv_com_1980_46/frame_0001.jpg",
      "source_filename": "frame_0002.jpg",
      "source_path": "corpus/05_frames/tv_com_1980_46/frame_0002.jpg",
      "timestamp_seconds": 0.25,
      "source_selection_reason": "interval",
      "selection_reason": "kept",
      "mean_luminance": 95.112,
      "median_luminance": 98.772,
      "dark_pixel_ratio": 0.104424,
      "similarity_to_previous_selected": null
    },
    {
      "frame_index": 2,
      "filename": "frame_0002.jpg",
      "path": "corpus/05_frames_selected/tv_com_1980_46/frame_0002.jpg",
      "source_filename": "frame_0005.jpg",
      "source_path": "corpus/05_frames/tv_com_1980_46/frame_0005.jpg",
      "timestamp_seconds": 1.0,
      "source_selection_reason": "interval",
      "selection_reason": "kept",
      "mean_luminance": 88.207,
      "median_luminance": 92.071,
      "dark_pixel_ratio": 0.131458,
      "similarity_to_previous_selected": 0.04506
    },
    {
      "frame_index": 3,
      "filename": "frame_0003.jpg",
      "path": "corpus/05_frames_selected/tv_com_1980_46/frame_0003.jpg",
      "source_filename": "frame_0006.jpg",
      "source_path": "corpus/05_frames/tv_com_1980_46/frame_0006.jpg",
      "timestamp_seconds": 1.25,
      "source_selection_reason": "interval",
      "selection_reason": "kept",
      "mean_luminance": 87.94,
      "median_luminance": 91.806,
      "dark_pixel_ratio": 0.13418,
      "similarity_to_previous_selected": 0.042743
    },
    {
      "frame_index": 4,
      "filename": "frame_0004.jpg",
      "path": "corpus/05_frames_selected/tv_com_1980_46/frame_0004.jpg",
      "source_filename": "frame_0007.jpg",
      "source_path": "corpus/05_frames/tv_com_1980_46/frame_0007.jpg",
      "timestamp_seconds": 1.5,
      "source_selection_reason": "interval",
      "selection_reason": "kept",
      "mean_luminance": 92.008,
      "median_luminance": 96.854,
      "dark_pixel_ratio": 0.125264,
      "similarity_to_previous_selected": 0.051474
    },
    {
      "frame_index": 5,
      "filename": "frame_0005.jpg",
      "path": "corpus/05_frames_selected/tv_com_1980_46/frame_0005.jpg",
      "source_filename": "frame_0008.jpg",
      "source_path": "corpus/05_frames/tv_com_1980_46/frame_0008.jpg",
      "timestamp_seconds": 1.75,
      "source_selection_reason": "interval",
      "selection_reason": "kept",
      "mean_luminance": 93.062,
      "median_luminance": 99.712,
      "dark_pixel_ratio": 0.12443,
      "similarity_to_previous_selected": 0.061006
    },
    {
      "frame_index": 6,
      "filename": "frame_0006.jpg",
      "path": "corpus/05_frames_selected/tv_com_1980_46/frame_0006.jpg",
      "source_filename": "frame_0009.jpg",
      "source_path": "corpus/05_frames/tv_com_1980_46/frame_0009.jpg",
      "timestamp_seconds": 2.0,
      "source_selection_reason": "interval",
      "selection_reason": "kept",
      "mean_luminance": 94.334,
      "median_luminance": 102.772,
      "dark_pixel_ratio": 0.119335,
      "similarity_to_previous_selected": 0.067287
    },
    {
      "frame_index": 7,
      "filename": "frame_0007.jpg",
      "path": "corpus/05_frames_selected/tv_com_1980_46/frame_0007.jpg",
      "source_filename": "frame_0010.jpg",
      "source_path": "corpus/05_frames/tv_com_1980_46/frame_0010.jpg",
      "timestamp_seconds": 2.25,
      "source_selection_reason": "interval",
      "selection_reason": "kept",
      "mean_luminance": 94.945,
      "median_luminance": 103.772,
      "dark_pixel_ratio": 0.111995,
      "similarity_to_previous_selected": 0.061956
    },
    {
      "frame_index": 8,
      "filename": "frame_0008.jpg",
      "path": "corpus/05_frames_selected/tv_com_1980_46/frame_0008.jpg",
      "source_filename": "frame_0011.jpg",
      "source_path": "corpus/05_frames/tv_com_1980_46/frame_0011.jpg",
      "timestamp_seconds": 2.5,
      "source_selection_reason": "interval",
      "selection_reason": "kept",
      "mean_luminance": 94.467,
      "median_luminance": 101.772,
      "dark_pixel_ratio": 0.111346,
      "similarity_to_previous_selected": 0.058502
    },
    {
      "frame_index": 9,
      "filename": "frame_0009.jpg",
      "path": "corpus/05_frames_selected/tv_com_1980_46/frame_0009.jpg",
      "source_filename": "frame_0012.jpg",
      "source_path": "corpus/05_frames/tv_com_1980_46/frame_0012.jpg",
      "timestamp_seconds": 2.75,
      "source_selection_reason": "interval",
      "selection_reason": "kept",
      "mean_luminance": 92.36,
      "median_luminance": 97.92,
      "dark_pixel_ratio": 0.122726,
      "similarity_to_previous_selected": 0.059521
    },
    {
      "frame_index": 10,
      "filename": "frame_0010.jpg",
      "path": "corpus/05_frames_selected/tv_com_1980_46/frame_0010.jpg",
      "source_filename": "frame_0013.jpg",
      "source_path": "corpus/05_frames/tv_com_1980_46/frame_0013.jpg",
      "timestamp_seconds": 3.0,
      "source_selection_reason": "interval",
      "selection_reason": "kept",
      "mean_luminance": 89.884,
      "median_luminance": 93.775,
      "dark_pixel_ratio": 0.138166,
      "similarity_to_previous_selected": 0.063507
    },
    {
      "frame_index": 11,
      "filename": "frame_0011.jpg",
      "path": "corpus/05_frames_selected/tv_com_1980_46/frame_0011.jpg",
      "source_filename": "frame_0014.jpg",
      "source_path": "corpus/05_frames/tv_com_1980_46/frame_0014.jpg",
      "timestamp_seconds": 3.25,
      "source_selection_reason": "interval",
      "selection_reason": "kept",
      "mean_luminance": 85.572,
      "median_luminance": 88.099,
      "dark_pixel_ratio": 0.181559,
      "similarity_to_previous_selected": 0.07024
    },
    {
      "frame_index": 12,
      "filename": "frame_0012.jpg",
      "path": "corpus/05_frames_selected/tv_com_1980_46/frame_0012.jpg",
      "source_filename": "frame_0015.jpg",
      "source_path": "corpus/05_frames/tv_com_1980_46/frame_0015.jpg",
      "timestamp_seconds": 3.5,
      "source_selection_reason": "interval",
      "selection_reason": "kept",
      "mean_luminance": 83.031,
      "median_luminance": 86.098,
      "dark_pixel_ratio": 0.214606,
      "similarity_to_previous_selected": 0.058464
    },
    {
      "frame_index": 13,
      "filename": "frame_0013.jpg",
      "path": "corpus/05_frames_selected/tv_com_1980_46/frame_0013.jpg",
      "source_filename": "frame_0016.jpg",
      "source_path": "corpus/05_frames/tv_com_1980_46/frame_0016.jpg",
      "timestamp_seconds": 3.75,
      "source_selection_reason": "interval",
      "selection_reason": "kept",
      "mean_luminance": 84.756,
      "median_luminance": 87.0,
      "dark_pixel_ratio": 0.19305,
      "similarity_to_previous_selected": 0.065445
    },
    {
      "frame_index": 14,
      "filename": "frame_0014.jpg",
      "path": "corpus/05_frames_selected/tv_com_1980_46/frame_0014.jpg",
      "source_filename": "frame_0017.jpg",
      "source_path": "corpus/05_frames/tv_com_1980_46/frame_0017.jpg",
      "timestamp_seconds": 4.0,
      "source_selection_reason": "interval",
      "selection_reason": "kept",
      "mean_luminance": 84.836,
      "median_luminance": 86.131,
      "dark_pixel_ratio": 0.186227,
      "similarity_to_previous_selected": 0.067023
    },
    {
      "frame_index": 15,
      "filename": "frame_0015.jpg",
      "path": "corpus/05_frames_selected/tv_com_1980_46/frame_0015.jpg",
      "source_filename": "frame_0018.jpg",
      "source_path": "corpus/05_frames/tv_com_1980_46/frame_0018.jpg",
      "timestamp_seconds": 4.25,
      "source_selection_reason": "interval",
      "selection_reason": "kept",
      "mean_luminance": 84.808,
      "median_luminance": 86.228,
      "dark_pixel_ratio": 0.197381,
      "similarity_to_previous_selected": 0.072538
    },
    {
      "frame_index": 16,
      "filename": "frame_0016.jpg",
      "path": "corpus/05_frames_selected/tv_com_1980_46/frame_0016.jpg",
      "source_filename": "frame_0019.jpg",
      "source_path": "corpus/05_frames/tv_com_1980_46/frame_0019.jpg",
      "timestamp_seconds": 4.5,
      "source_selection_reason": "interval",
      "selection_reason": "kept",
      "mean_luminance": 84.804,
      "median_luminance": 86.228,
      "dark_pixel_ratio": 0.204307,
      "similarity_to_previous_selected": 0.075532
    },
    {
      "frame_index": 17,
      "filename": "frame_0017.jpg",
      "path": "corpus/05_frames_selected/tv_com_1980_46/frame_0017.jpg",
      "source_filename": "frame_0020.jpg",
      "source_path": "corpus/05_frames/tv_com_1980_46/frame_0020.jpg",
      "timestamp_seconds": 4.75,
      "source_selection_reason": "interval",
      "selection_reason": "kept",
      "mean_luminance": 88.919,
      "median_luminance": 94.806,
      "dark_pixel_ratio": 0.188983,
      "similarity_to_previous_selected": 0.081147
    },
    {
      "frame_index": 18,
      "filename": "frame_0018.jpg",
      "path": "corpus/05_frames_selected/tv_com_1980_46/frame_0018.jpg",
      "source_filename": "frame_0021.jpg",
      "source_path": "corpus/05_frames/tv_com_1980_46/frame_0021.jpg",
      "timestamp_seconds": 5.0,
      "source_selection_reason": "interval",
      "selection_reason": "kept",
      "mean_luminance": 89.992,
      "median_luminance": 97.133,
      "dark_pixel_ratio": 0.198669,
      "similarity_to_previous_selected": 0.077459
    },
    {
      "frame_index": 19,
      "filename": "frame_0019.jpg",
      "path": "corpus/05_frames_selected/tv_com_1980_46/frame_0019.jpg",
      "source_filename": "frame_0022.jpg",
      "source_path": "corpus/05_frames/tv_com_1980_46/frame_0022.jpg",
      "timestamp_seconds": 5.25,
      "source_selection_reason": "interval",
      "selection_reason": "kept",
      "mean_luminance": 88.579,
      "median_luminance": 94.118,
      "dark_pixel_ratio": 0.212194,
      "similarity_to_previous_selected": 0.062404
    },
    {
      "frame_index": 20,
      "filename": "frame_0020.jpg",
      "path": "corpus/05_frames_selected/tv_com_1980_46/frame_0020.jpg",
      "source_filename": "frame_0023.jpg",
      "source_path": "corpus/05_frames/tv_com_1980_46/frame_0023.jpg",
      "timestamp_seconds": 5.5,
      "source_selection_reason": "interval",
      "selection_reason": "kept",
      "mean_luminance": 85.745,
      "median_luminance": 90.063,
      "dark_pixel_ratio": 0.234899,
      "similarity_to_previous_selected": 0.059926
    },
    {
      "frame_index": 21,
      "filename": "frame_0021.jpg",
      "path": "corpus/05_frames_selected/tv_com_1980_46/frame_0021.jpg",
      "source_filename": "frame_0024.jpg",
      "source_path": "corpus/05_frames/tv_com_1980_46/frame_0024.jpg",
      "timestamp_seconds": 5.75,
      "source_selection_reason": "interval",
      "selection_reason": "kept",
      "mean_luminance": 83.322,
      "median_luminance": 87.088,
      "dark_pixel_ratio": 0.253402,
      "similarity_to_previous_selected": 0.067999
    },
    {
      "frame_index": 22,
      "filename": "frame_0022.jpg",
      "path": "corpus/05_frames_selected/tv_com_1980_46/frame_0022.jpg",
      "source_filename": "frame_0025.jpg",
      "source_path": "corpus/05_frames/tv_com_1980_46/frame_0025.jpg",
      "timestamp_seconds": 6.0,
      "source_selection_reason": "interval",
      "selection_reason": "kept",
      "mean_luminance": 80.313,
      "median_luminance": 79.088,
      "dark_pixel_ratio": 0.251555,
      "similarity_to_previous_selected": 0.083111
    },
    {
      "frame_index": 23,
      "filename": "frame_0023.jpg",
      "path": "corpus/05_frames_selected/tv_com_1980_46/frame_0023.jpg",
      "source_filename": "frame_0026.jpg",
      "source_path": "corpus/05_frames/tv_com_1980_46/frame_0026.jpg",
      "timestamp_seconds": 6.25,
      "source_selection_reason": "interval",
      "selection_reason": "kept",
      "mean_luminance": 82.6,
      "median_luminance": 80.832,
      "dark_pixel_ratio": 0.224964,
      "similarity_to_previous_selected": 0.073434
    },
    {
      "frame_index": 24,
      "filename": "frame_0024.jpg",
      "path": "corpus/05_frames_selected/tv_com_1980_46/frame_0024.jpg",
      "source_filename": "frame_0027.jpg",
      "source_path": "corpus/05_frames/tv_com_1980_46/frame_0027.jpg",
      "timestamp_seconds": 6.5,
      "source_selection_reason": "interval",
      "selection_reason": "kept",
      "mean_luminance": 85.97,
      "median_luminance": 89.86,
      "dark_pixel_ratio": 0.217152,
      "similarity_to_previous_selected": 0.08197
    },
    {
      "frame_index": 25,
      "filename": "frame_0025.jpg",
      "path": "corpus/05_frames_selected/tv_com_1980_46/frame_0025.jpg",
      "source_filename": "frame_0028.jpg",
      "source_path": "corpus/05_frames/tv_com_1980_46/frame_0028.jpg",
      "timestamp_seconds": 6.75,
      "source_selection_reason": "interval",
      "selection_reason": "kept",
      "mean_luminance": 87.998,
      "median_luminance": 90.843,
      "dark_pixel_ratio": 0.211661,
      "similarity_to_previous_selected": 0.102623
    },
    {
      "frame_index": 26,
      "filename": "frame_0026.jpg",
      "path": "corpus/05_frames_selected/tv_com_1980_46/frame_0026.jpg",
      "source_filename": "frame_0029.jpg",
      "source_path": "corpus/05_frames/tv_com_1980_46/frame_0029.jpg",
      "timestamp_seconds": 7.0,
      "source_selection_reason": "interval",
      "selection_reason": "kept",
      "mean_luminance": 83.975,
      "median_luminance": 88.791,
      "dark_pixel_ratio": 0.224659,
      "similarity_to_previous_selected": 0.133211
    },
    {
      "frame_index": 27,
      "filename": "frame_0027.jpg",
      "path": "corpus/05_frames_selected/tv_com_1980_46/frame_0027.jpg",
      "source_filename": "frame_0030.jpg",
      "source_path": "corpus/05_frames/tv_com_1980_46/frame_0030.jpg",
      "timestamp_seconds": 7.25,
      "source_selection_reason": "interval",
      "selection_reason": "kept",
      "mean_luminance": 84.942,
      "median_luminance": 85.017,
      "dark_pixel_ratio": 0.197157,
      "similarity_to_previous_selected": 0.142666
    },
    {
      "frame_index": 28,
      "filename": "frame_0028.jpg",
      "path": "corpus/05_frames_selected/tv_com_1980_46/frame_0028.jpg",
      "source_filename": "frame_0031.jpg",
      "source_path": "corpus/05_frames/tv_com_1980_46/frame_0031.jpg",
      "timestamp_seconds": 7.5,
      "source_selection_reason": "interval",
      "selection_reason": "kept",
      "mean_luminance": 102.241,
      "median_luminance": 115.997,
      "dark_pixel_ratio": 0.092233,
      "similarity_to_previous_selected": 0.140778
    },
    {
      "frame_index": 29,
      "filename": "frame_0029.jpg",
      "path": "corpus/05_frames_selected/tv_com_1980_46/frame_0029.jpg",
      "source_filename": "frame_0032.jpg",
      "source_path": "corpus/05_frames/tv_com_1980_46/frame_0032.jpg",
      "timestamp_seconds": 7.75,
      "source_selection_reason": "interval",
      "selection_reason": "kept",
      "mean_luminance": 110.98,
      "median_luminance": 125.827,
      "dark_pixel_ratio": 0.069187,
      "similarity_to_previous_selected": 0.103451
    },
    {
      "frame_index": 30,
      "filename": "frame_0030.jpg",
      "path": "corpus/05_frames_selected/tv_com_1980_46/frame_0030.jpg",
      "source_filename": "frame_0033.jpg",
      "source_path": "corpus/05_frames/tv_com_1980_46/frame_0033.jpg",
      "timestamp_seconds": 8.0,
      "source_selection_reason": "interval",
      "selection_reason": "kept",
      "mean_luminance": 86.83,
      "median_luminance": 91.687,
      "dark_pixel_ratio": 0.162157,
      "similarity_to_previous_selected": 0.171722
    },
    {
      "frame_index": 31,
      "filename": "frame_0031.jpg",
      "path": "corpus/05_frames_selected/tv_com_1980_46/frame_0031.jpg",
      "source_filename": "frame_0036.jpg",
      "source_path": "corpus/05_frames/tv_com_1980_46/frame_0036.jpg",
      "timestamp_seconds": 8.75,
      "source_selection_reason": "interval",
      "selection_reason": "kept",
      "mean_luminance": 88.952,
      "median_luminance": 97.844,
      "dark_pixel_ratio": 0.168098,
      "similarity_to_previous_selected": 0.059861
    },
    {
      "frame_index": 32,
      "filename": "frame_0032.jpg",
      "path": "corpus/05_frames_selected/tv_com_1980_46/frame_0032.jpg",
      "source_filename": "frame_0037.jpg",
      "source_path": "corpus/05_frames/tv_com_1980_46/frame_0037.jpg",
      "timestamp_seconds": 9.0,
      "source_selection_reason": "interval",
      "selection_reason": "kept",
      "mean_luminance": 87.941,
      "median_luminance": 98.131,
      "dark_pixel_ratio": 0.180601,
      "similarity_to_previous_selected": 0.040663
    },
    {
      "frame_index": 33,
      "filename": "frame_0033.jpg",
      "path": "corpus/05_frames_selected/tv_com_1980_46/frame_0033.jpg",
      "source_filename": "frame_0038.jpg",
      "source_path": "corpus/05_frames/tv_com_1980_46/frame_0038.jpg",
      "timestamp_seconds": 9.25,
      "source_selection_reason": "interval",
      "selection_reason": "kept",
      "mean_luminance": 86.205,
      "median_luminance": 97.082,
      "dark_pixel_ratio": 0.189559,
      "similarity_to_previous_selected": 0.046867
    },
    {
      "frame_index": 34,
      "filename": "frame_0034.jpg",
      "path": "corpus/05_frames_selected/tv_com_1980_46/frame_0034.jpg",
      "source_filename": "frame_0039.jpg",
      "source_path": "corpus/05_frames/tv_com_1980_46/frame_0039.jpg",
      "timestamp_seconds": 9.5,
      "source_selection_reason": "interval",
      "selection_reason": "kept",
      "mean_luminance": 86.398,
      "median_luminance": 97.784,
      "dark_pixel_ratio": 0.187597,
      "similarity_to_previous_selected": 0.051383
    },
    {
      "frame_index": 35,
      "filename": "frame_0035.jpg",
      "path": "corpus/05_frames_selected/tv_com_1980_46/frame_0035.jpg",
      "source_filename": "frame_0040.jpg",
      "source_path": "corpus/05_frames/tv_com_1980_46/frame_0040.jpg",
      "timestamp_seconds": 9.75,
      "source_selection_reason": "interval",
      "selection_reason": "kept",
      "mean_luminance": 87.122,
      "median_luminance": 98.712,
      "dark_pixel_ratio": 0.186867,
      "similarity_to_previous_selected": 0.066031
    },
    {
      "frame_index": 36,
      "filename": "frame_0036.jpg",
      "path": "corpus/05_frames_selected/tv_com_1980_46/frame_0036.jpg",
      "source_filename": "frame_0041.jpg",
      "source_path": "corpus/05_frames/tv_com_1980_46/frame_0041.jpg",
      "timestamp_seconds": 10.0,
      "source_selection_reason": "interval",
      "selection_reason": "kept",
      "mean_luminance": 87.128,
      "median_luminance": 99.228,
      "dark_pixel_ratio": 0.1858,
      "similarity_to_previous_selected": 0.073993
    },
    {
      "frame_index": 37,
      "filename": "frame_0037.jpg",
      "path": "corpus/05_frames_selected/tv_com_1980_46/frame_0037.jpg",
      "source_filename": "frame_0042.jpg",
      "source_path": "corpus/05_frames/tv_com_1980_46/frame_0042.jpg",
      "timestamp_seconds": 10.25,
      "source_selection_reason": "interval",
      "selection_reason": "kept",
      "mean_luminance": 88.094,
      "median_luminance": 100.969,
      "dark_pixel_ratio": 0.192783,
      "similarity_to_previous_selected": 0.083019
    },
    {
      "frame_index": 38,
      "filename": "frame_0038.jpg",
      "path": "corpus/05_frames_selected/tv_com_1980_46/frame_0038.jpg",
      "source_filename": "frame_0043.jpg",
      "source_path": "corpus/05_frames/tv_com_1980_46/frame_0043.jpg",
      "timestamp_seconds": 10.5,
      "source_selection_reason": "interval",
      "selection_reason": "kept",
      "mean_luminance": 89.194,
      "median_luminance": 104.712,
      "dark_pixel_ratio": 0.200525,
      "similarity_to_previous_selected": 0.095523
    },
    {
      "frame_index": 39,
      "filename": "frame_0039.jpg",
      "path": "corpus/05_frames_selected/tv_com_1980_46/frame_0039.jpg",
      "source_filename": "frame_0044.jpg",
      "source_path": "corpus/05_frames/tv_com_1980_46/frame_0044.jpg",
      "timestamp_seconds": 10.75,
      "source_selection_reason": "interval",
      "selection_reason": "kept",
      "mean_luminance": 89.594,
      "median_luminance": 105.168,
      "dark_pixel_ratio": 0.18847,
      "similarity_to_previous_selected": 0.099452
    },
    {
      "frame_index": 40,
      "filename": "frame_0040.jpg",
      "path": "corpus/05_frames_selected/tv_com_1980_46/frame_0040.jpg",
      "source_filename": "frame_0045.jpg",
      "source_path": "corpus/05_frames/tv_com_1980_46/frame_0045.jpg",
      "timestamp_seconds": 11.0,
      "source_selection_reason": "interval",
      "selection_reason": "kept",
      "mean_luminance": 83.516,
      "median_luminance": 96.951,
      "dark_pixel_ratio": 0.244837,
      "similarity_to_previous_selected": 0.107495
    },
    {
      "frame_index": 41,
      "filename": "frame_0041.jpg",
      "path": "corpus/05_frames_selected/tv_com_1980_46/frame_0041.jpg",
      "source_filename": "frame_0046.jpg",
      "source_path": "corpus/05_frames/tv_com_1980_46/frame_0046.jpg",
      "timestamp_seconds": 11.25,
      "source_selection_reason": "interval",
      "selection_reason": "kept",
      "mean_luminance": 80.52,
      "median_luminance": 92.843,
      "dark_pixel_ratio": 0.267499,
      "similarity_to_previous_selected": 0.125479
    },
    {
      "frame_index": 42,
      "filename": "frame_0042.jpg",
      "path": "corpus/05_frames_selected/tv_com_1980_46/frame_0042.jpg",
      "source_filename": "frame_0047.jpg",
      "source_path": "corpus/05_frames/tv_com_1980_46/frame_0047.jpg",
      "timestamp_seconds": 11.5,
      "source_selection_reason": "interval",
      "selection_reason": "kept",
      "mean_luminance": 76.042,
      "median_luminance": 74.033,
      "dark_pixel_ratio": 0.202015,
      "similarity_to_previous_selected": 0.128167
    },
    {
      "frame_index": 43,
      "filename": "frame_0043.jpg",
      "path": "corpus/05_frames_selected/tv_com_1980_46/frame_0043.jpg",
      "source_filename": "frame_0048.jpg",
      "source_path": "corpus/05_frames/tv_com_1980_46/frame_0048.jpg",
      "timestamp_seconds": 11.75,
      "source_selection_reason": "interval",
      "selection_reason": "kept",
      "mean_luminance": 88.456,
      "median_luminance": 93.869,
      "dark_pixel_ratio": 0.245242,
      "similarity_to_previous_selected": 0.202325
    },
    {
      "frame_index": 44,
      "filename": "frame_0044.jpg",
      "path": "corpus/05_frames_selected/tv_com_1980_46/frame_0044.jpg",
      "source_filename": "frame_0049.jpg",
      "source_path": "corpus/05_frames/tv_com_1980_46/frame_0049.jpg",
      "timestamp_seconds": 12.0,
      "source_selection_reason": "interval",
      "selection_reason": "kept",
      "mean_luminance": 87.729,
      "median_luminance": 91.649,
      "dark_pixel_ratio": 0.21934,
      "similarity_to_previous_selected": 0.121703
    },
    {
      "frame_index": 45,
      "filename": "frame_0045.jpg",
      "path": "corpus/05_frames_selected/tv_com_1980_46/frame_0045.jpg",
      "source_filename": "frame_0050.jpg",
      "source_path": "corpus/05_frames/tv_com_1980_46/frame_0050.jpg",
      "timestamp_seconds": 12.25,
      "source_selection_reason": "interval",
      "selection_reason": "kept",
      "mean_luminance": 85.148,
      "median_luminance": 89.228,
      "dark_pixel_ratio": 0.210465,
      "similarity_to_previous_selected": 0.10607
    },
    {
      "frame_index": 46,
      "filename": "frame_0046.jpg",
      "path": "corpus/05_frames_selected/tv_com_1980_46/frame_0046.jpg",
      "source_filename": "frame_0051.jpg",
      "source_path": "corpus/05_frames/tv_com_1980_46/frame_0051.jpg",
      "timestamp_seconds": 12.5,
      "source_selection_reason": "interval",
      "selection_reason": "kept",
      "mean_luminance": 82.596,
      "median_luminance": 87.042,
      "dark_pixel_ratio": 0.206269,
      "similarity_to_previous_selected": 0.097989
    },
    {
      "frame_index": 47,
      "filename": "frame_0047.jpg",
      "path": "corpus/05_frames_selected/tv_com_1980_46/frame_0047.jpg",
      "source_filename": "frame_0052.jpg",
      "source_path": "corpus/05_frames/tv_com_1980_46/frame_0052.jpg",
      "timestamp_seconds": 12.75,
      "source_selection_reason": "interval",
      "selection_reason": "kept",
      "mean_luminance": 80.704,
      "median_luminance": 84.877,
      "dark_pixel_ratio": 0.206923,
      "similarity_to_previous_selected": 0.102068
    },
    {
      "frame_index": 48,
      "filename": "frame_0048.jpg",
      "path": "corpus/05_frames_selected/tv_com_1980_46/frame_0048.jpg",
      "source_filename": "frame_0053.jpg",
      "source_path": "corpus/05_frames/tv_com_1980_46/frame_0053.jpg",
      "timestamp_seconds": 13.0,
      "source_selection_reason": "interval",
      "selection_reason": "kept",
      "mean_luminance": 79.627,
      "median_luminance": 83.731,
      "dark_pixel_ratio": 0.212314,
      "similarity_to_previous_selected": 0.096764
    },
    {
      "frame_index": 49,
      "filename": "frame_0049.jpg",
      "path": "corpus/05_frames_selected/tv_com_1980_46/frame_0049.jpg",
      "source_filename": "frame_0054.jpg",
      "source_path": "corpus/05_frames/tv_com_1980_46/frame_0054.jpg",
      "timestamp_seconds": 13.25,
      "source_selection_reason": "interval",
      "selection_reason": "kept",
      "mean_luminance": 78.021,
      "median_luminance": 82.86,
      "dark_pixel_ratio": 0.226863,
      "similarity_to_previous_selected": 0.10607
    },
    {
      "frame_index": 50,
      "filename": "frame_0050.jpg",
      "path": "corpus/05_frames_selected/tv_com_1980_46/frame_0050.jpg",
      "source_filename": "frame_0055.jpg",
      "source_path": "corpus/05_frames/tv_com_1980_46/frame_0055.jpg",
      "timestamp_seconds": 13.5,
      "source_selection_reason": "interval",
      "selection_reason": "kept",
      "mean_luminance": 76.593,
      "median_luminance": 81.685,
      "dark_pixel_ratio": 0.232528,
      "similarity_to_previous_selected": 0.102068
    },
    {
      "frame_index": 51,
      "filename": "frame_0051.jpg",
      "path": "corpus/05_frames_selected/tv_com_1980_46/frame_0051.jpg",
      "source_filename": "frame_0056.jpg",
      "source_path": "corpus/05_frames/tv_com_1980_46/frame_0056.jpg",
      "timestamp_seconds": 13.75,
      "source_selection_reason": "interval",
      "selection_reason": "kept",
      "mean_luminance": 76.589,
      "median_luminance": 81.843,
      "dark_pixel_ratio": 0.232458,
      "similarity_to_previous_selected": 0.102941
    },
    {
      "frame_index": 52,
      "filename": "frame_0052.jpg",
      "path": "corpus/05_frames_selected/tv_com_1980_46/frame_0052.jpg",
      "source_filename": "frame_0057.jpg",
      "source_path": "corpus/05_frames/tv_com_1980_46/frame_0057.jpg",
      "timestamp_seconds": 14.0,
      "source_selection_reason": "interval",
      "selection_reason": "kept",
      "mean_luminance": 78.032,
      "median_luminance": 82.749,
      "dark_pixel_ratio": 0.22618,
      "similarity_to_previous_selected": 0.09293
    },
    {
      "frame_index": 53,
      "filename": "frame_0053.jpg",
      "path": "corpus/05_frames_selected/tv_com_1980_46/frame_0053.jpg",
      "source_filename": "frame_0058.jpg",
      "source_path": "corpus/05_frames/tv_com_1980_46/frame_0058.jpg",
      "timestamp_seconds": 14.25,
      "source_selection_reason": "interval",
      "selection_reason": "kept",
      "mean_luminance": 78.583,
      "median_luminance": 82.816,
      "dark_pixel_ratio": 0.222075,
      "similarity_to_previous_selected": 0.092827
    },
    {
      "frame_index": 54,
      "filename": "frame_0054.jpg",
      "path": "corpus/05_frames_selected/tv_com_1980_46/frame_0054.jpg",
      "source_filename": "frame_0059.jpg",
      "source_path": "corpus/05_frames/tv_com_1980_46/frame_0059.jpg",
      "timestamp_seconds": 14.5,
      "source_selection_reason": "interval",
      "selection_reason": "kept",
      "mean_luminance": 80.353,
      "median_luminance": 84.86,
      "dark_pixel_ratio": 0.211064,
      "similarity_to_previous_selected": 0.076949
    },
    {
      "frame_index": 55,
      "filename": "frame_0055.jpg",
      "path": "corpus/05_frames_selected/tv_com_1980_46/frame_0055.jpg",
      "source_filename": "frame_0060.jpg",
      "source_path": "corpus/05_frames/tv_com_1980_46/frame_0060.jpg",
      "timestamp_seconds": 14.75,
      "source_selection_reason": "interval",
      "selection_reason": "kept",
      "mean_luminance": 80.699,
      "median_luminance": 85.871,
      "dark_pixel_ratio": 0.208487,
      "similarity_to_previous_selected": 0.080817
    },
    {
      "frame_index": 56,
      "filename": "frame_0056.jpg",
      "path": "corpus/05_frames_selected/tv_com_1980_46/frame_0056.jpg",
      "source_filename": "frame_0061.jpg",
      "source_path": "corpus/05_frames/tv_com_1980_46/frame_0061.jpg",
      "timestamp_seconds": 15.0,
      "source_selection_reason": "interval",
      "selection_reason": "kept",
      "mean_luminance": 80.677,
      "median_luminance": 85.888,
      "dark_pixel_ratio": 0.207117,
      "similarity_to_previous_selected": 0.061443
    },
    {
      "frame_index": 57,
      "filename": "frame_0057.jpg",
      "path": "corpus/05_frames_selected/tv_com_1980_46/frame_0057.jpg",
      "source_filename": "frame_0062.jpg",
      "source_path": "corpus/05_frames/tv_com_1980_46/frame_0062.jpg",
      "timestamp_seconds": 15.25,
      "source_selection_reason": "interval",
      "selection_reason": "kept",
      "mean_luminance": 81.551,
      "median_luminance": 86.888,
      "dark_pixel_ratio": 0.205248,
      "similarity_to_previous_selected": 0.052953
    },
    {
      "frame_index": 58,
      "filename": "frame_0058.jpg",
      "path": "corpus/05_frames_selected/tv_com_1980_46/frame_0058.jpg",
      "source_filename": "frame_0063.jpg",
      "source_path": "corpus/05_frames/tv_com_1980_46/frame_0063.jpg",
      "timestamp_seconds": 15.5,
      "source_selection_reason": "interval",
      "selection_reason": "kept",
      "mean_luminance": 82.277,
      "median_luminance": 86.888,
      "dark_pixel_ratio": 0.201509,
      "similarity_to_previous_selected": 0.045002
    },
    {
      "frame_index": 59,
      "filename": "frame_0059.jpg",
      "path": "corpus/05_frames_selected/tv_com_1980_46/frame_0059.jpg",
      "source_filename": "frame_0065.jpg",
      "source_path": "corpus/05_frames/tv_com_1980_46/frame_0065.jpg",
      "timestamp_seconds": 16.0,
      "source_selection_reason": "interval",
      "selection_reason": "kept",
      "mean_luminance": 80.432,
      "median_luminance": 83.305,
      "dark_pixel_ratio": 0.218126,
      "similarity_to_previous_selected": 0.0599
    },
    {
      "frame_index": 60,
      "filename": "frame_0060.jpg",
      "path": "corpus/05_frames_selected/tv_com_1980_46/frame_0060.jpg",
      "source_filename": "frame_0067.jpg",
      "source_path": "corpus/05_frames/tv_com_1980_46/frame_0067.jpg",
      "timestamp_seconds": 16.5,
      "source_selection_reason": "interval",
      "selection_reason": "kept",
      "mean_luminance": 82.063,
      "median_luminance": 84.959,
      "dark_pixel_ratio": 0.208797,
      "similarity_to_previous_selected": 0.038641
    },
    {
      "frame_index": 61,
      "filename": "frame_0061.jpg",
      "path": "corpus/05_frames_selected/tv_com_1980_46/frame_0061.jpg",
      "source_filename": "frame_0070.jpg",
      "source_path": "corpus/05_frames/tv_com_1980_46/frame_0070.jpg",
      "timestamp_seconds": 17.25,
      "source_selection_reason": "interval",
      "selection_reason": "kept",
      "mean_luminance": 80.49,
      "median_luminance": 83.116,
      "dark_pixel_ratio": 0.216363,
      "similarity_to_previous_selected": 0.046032
    },
    {
      "frame_index": 62,
      "filename": "frame_0062.jpg",
      "path": "corpus/05_frames_selected/tv_com_1980_46/frame_0062.jpg",
      "source_filename": "frame_0073.jpg",
      "source_path": "corpus/05_frames/tv_com_1980_46/frame_0073.jpg",
      "timestamp_seconds": 18.0,
      "source_selection_reason": "interval",
      "selection_reason": "kept",
      "mean_luminance": 80.857,
      "median_luminance": 83.25,
      "dark_pixel_ratio": 0.218434,
      "similarity_to_previous_selected": 0.046772
    },
    {
      "frame_index": 63,
      "filename": "frame_0063.jpg",
      "path": "corpus/05_frames_selected/tv_com_1980_46/frame_0063.jpg",
      "source_filename": "frame_0075.jpg",
      "source_path": "corpus/05_frames/tv_com_1980_46/frame_0075.jpg",
      "timestamp_seconds": 18.5,
      "source_selection_reason": "interval",
      "selection_reason": "kept",
      "mean_luminance": 82.104,
      "median_luminance": 85.042,
      "dark_pixel_ratio": 0.210777,
      "similarity_to_previous_selected": 0.037063
    },
    {
      "frame_index": 64,
      "filename": "frame_0064.jpg",
      "path": "corpus/05_frames_selected/tv_com_1980_46/frame_0064.jpg",
      "source_filename": "frame_0080.jpg",
      "source_path": "corpus/05_frames/tv_com_1980_46/frame_0080.jpg",
      "timestamp_seconds": 19.75,
      "source_selection_reason": "interval",
      "selection_reason": "kept",
      "mean_luminance": 85.536,
      "median_luminance": 89.94,
      "dark_pixel_ratio": 0.195586,
      "similarity_to_previous_selected": 0.040901
    },
    {
      "frame_index": 65,
      "filename": "frame_0065.jpg",
      "path": "corpus/05_frames_selected/tv_com_1980_46/frame_0065.jpg",
      "source_filename": "frame_0085.jpg",
      "source_path": "corpus/05_frames/tv_com_1980_46/frame_0085.jpg",
      "timestamp_seconds": 21.0,
      "source_selection_reason": "interval",
      "selection_reason": "kept",
      "mean_luminance": 84.107,
      "median_luminance": 87.869,
      "dark_pixel_ratio": 0.201936,
      "similarity_to_previous_selected": 0.041065
    },
    {
      "frame_index": 66,
      "filename": "frame_0066.jpg",
      "path": "corpus/05_frames_selected/tv_com_1980_46/frame_0066.jpg",
      "source_filename": "frame_0086.jpg",
      "source_path": "corpus/05_frames/tv_com_1980_46/frame_0086.jpg",
      "timestamp_seconds": 21.25,
      "source_selection_reason": "interval",
      "selection_reason": "kept",
      "mean_luminance": 83.569,
      "median_luminance": 88.122,
      "dark_pixel_ratio": 0.210621,
      "similarity_to_previous_selected": 0.051352
    },
    {
      "frame_index": 67,
      "filename": "frame_0067.jpg",
      "path": "corpus/05_frames_selected/tv_com_1980_46/frame_0067.jpg",
      "source_filename": "frame_0087.jpg",
      "source_path": "corpus/05_frames/tv_com_1980_46/frame_0087.jpg",
      "timestamp_seconds": 21.5,
      "source_selection_reason": "interval",
      "selection_reason": "kept",
      "mean_luminance": 85.401,
      "median_luminance": 91.632,
      "dark_pixel_ratio": 0.213277,
      "similarity_to_previous_selected": 0.053925
    },
    {
      "frame_index": 68,
      "filename": "frame_0068.jpg",
      "path": "corpus/05_frames_selected/tv_com_1980_46/frame_0068.jpg",
      "source_filename": "frame_0088.jpg",
      "source_path": "corpus/05_frames/tv_com_1980_46/frame_0088.jpg",
      "timestamp_seconds": 21.75,
      "source_selection_reason": "interval",
      "selection_reason": "kept",
      "mean_luminance": 90.039,
      "median_luminance": 100.888,
      "dark_pixel_ratio": 0.198387,
      "similarity_to_previous_selected": 0.047097
    },
    {
      "frame_index": 69,
      "filename": "frame_0069.jpg",
      "path": "corpus/05_frames_selected/tv_com_1980_46/frame_0069.jpg",
      "source_filename": "frame_0089.jpg",
      "source_path": "corpus/05_frames/tv_com_1980_46/frame_0089.jpg",
      "timestamp_seconds": 22.0,
      "source_selection_reason": "interval",
      "selection_reason": "kept",
      "mean_luminance": 93.777,
      "median_luminance": 106.888,
      "dark_pixel_ratio": 0.184362,
      "similarity_to_previous_selected": 0.045064
    },
    {
      "frame_index": 70,
      "filename": "frame_0070.jpg",
      "path": "corpus/05_frames_selected/tv_com_1980_46/frame_0070.jpg",
      "source_filename": "frame_0090.jpg",
      "source_path": "corpus/05_frames/tv_com_1980_46/frame_0090.jpg",
      "timestamp_seconds": 22.25,
      "source_selection_reason": "interval",
      "selection_reason": "kept",
      "mean_luminance": 93.995,
      "median_luminance": 108.019,
      "dark_pixel_ratio": 0.19581,
      "similarity_to_previous_selected": 0.039947
    },
    {
      "frame_index": 71,
      "filename": "frame_0071.jpg",
      "path": "corpus/05_frames_selected/tv_com_1980_46/frame_0071.jpg",
      "source_filename": "frame_0091.jpg",
      "source_path": "corpus/05_frames/tv_com_1980_46/frame_0091.jpg",
      "timestamp_seconds": 22.5,
      "source_selection_reason": "interval",
      "selection_reason": "kept",
      "mean_luminance": 52.357,
      "median_luminance": 61.894,
      "dark_pixel_ratio": 0.276017,
      "similarity_to_previous_selected": 0.16569
    }
  ],
  "rejected_frames": [
    {
      "source_filename": "frame_0001.jpg",
      "source_path": "corpus/05_frames/tv_com_1980_46/frame_0001.jpg",
      "timestamp_seconds": 0.0,
      "rejection_reason": "dark_frame",
      "mean_luminance": 0.003,
      "median_luminance": 0.0,
      "dark_pixel_ratio": 0.999991,
      "similarity_to_selected_frame": null,
      "duplicate_of_source_filename": null
    },
    {
      "source_filename": "frame_0003.jpg",
      "source_path": "corpus/05_frames/tv_com_1980_46/frame_0003.jpg",
      "timestamp_seconds": 0.5,
      "rejection_reason": "duplicate_frame",
      "mean_luminance": 90.302,
      "median_luminance": 94.772,
      "dark_pixel_ratio": 0.120108,
      "similarity_to_selected_frame": 0.021557,
      "duplicate_of_source_filename": "frame_0002.jpg"
    },
    {
      "source_filename": "frame_0004.jpg",
      "source_path": "corpus/05_frames/tv_com_1980_46/frame_0004.jpg",
      "timestamp_seconds": 0.75,
      "rejection_reason": "duplicate_frame",
      "mean_luminance": 89.0,
      "median_luminance": 93.088,
      "dark_pixel_ratio": 0.129541,
      "similarity_to_selected_frame": 0.028853,
      "duplicate_of_source_filename": "frame_0002.jpg"
    },
    {
      "source_filename": "frame_0034.jpg",
      "source_path": "corpus/05_frames/tv_com_1980_46/frame_0034.jpg",
      "timestamp_seconds": 8.25,
      "rejection_reason": "duplicate_frame",
      "mean_luminance": 87.093,
      "median_luminance": 92.965,
      "dark_pixel_ratio": 0.161745,
      "similarity_to_selected_frame": 0.013779,
      "duplicate_of_source_filename": "frame_0033.jpg"
    },
    {
      "source_filename": "frame_0035.jpg",
      "source_path": "corpus/05_frames/tv_com_1980_46/frame_0035.jpg",
      "timestamp_seconds": 8.5,
      "rejection_reason": "duplicate_frame",
      "mean_luminance": 87.189,
      "median_luminance": 93.825,
      "dark_pixel_ratio": 0.166854,
      "similarity_to_selected_frame": 0.031725,
      "duplicate_of_source_filename": "frame_0033.jpg"
    },
    {
      "source_filename": "frame_0064.jpg",
      "source_path": "corpus/05_frames/tv_com_1980_46/frame_0064.jpg",
      "timestamp_seconds": 15.75,
      "rejection_reason": "duplicate_frame",
      "mean_luminance": 81.76,
      "median_luminance": 85.937,
      "dark_pixel_ratio": 0.204151,
      "similarity_to_selected_frame": 0.032732,
      "duplicate_of_source_filename": "frame_0063.jpg"
    },
    {
      "source_filename": "frame_0066.jpg",
      "source_path": "corpus/05_frames/tv_com_1980_46/frame_0066.jpg",
      "timestamp_seconds": 16.25,
      "rejection_reason": "duplicate_frame",
      "mean_luminance": 81.184,
      "median_luminance": 84.025,
      "dark_pixel_ratio": 0.214826,
      "similarity_to_selected_frame": 0.025046,
      "duplicate_of_source_filename": "frame_0065.jpg"
    },
    {
      "source_filename": "frame_0068.jpg",
      "source_path": "corpus/05_frames/tv_com_1980_46/frame_0068.jpg",
      "timestamp_seconds": 16.75,
      "rejection_reason": "duplicate_frame",
      "mean_luminance": 81.615,
      "median_luminance": 84.695,
      "dark_pixel_ratio": 0.208449,
      "similarity_to_selected_frame": 0.016858,
      "duplicate_of_source_filename": "frame_0067.jpg"
    },
    {
      "source_filename": "frame_0069.jpg",
      "source_path": "corpus/05_frames/tv_com_1980_46/frame_0069.jpg",
      "timestamp_seconds": 17.0,
      "rejection_reason": "duplicate_frame",
      "mean_luminance": 81.561,
      "median_luminance": 84.23,
      "dark_pixel_ratio": 0.21165,
      "similarity_to_selected_frame": 0.032089,
      "duplicate_of_source_filename": "frame_0067.jpg"
    },
    {
      "source_filename": "frame_0071.jpg",
      "source_path": "corpus/05_frames/tv_com_1980_46/frame_0071.jpg",
      "timestamp_seconds": 17.5,
      "rejection_reason": "duplicate_frame",
      "mean_luminance": 80.211,
      "median_luminance": 82.828,
      "dark_pixel_ratio": 0.219082,
      "similarity_to_selected_frame": 0.015782,
      "duplicate_of_source_filename": "frame_0070.jpg"
    },
    {
      "source_filename": "frame_0072.jpg",
      "source_path": "corpus/05_frames/tv_com_1980_46/frame_0072.jpg",
      "timestamp_seconds": 17.75,
      "rejection_reason": "duplicate_frame",
      "mean_luminance": 80.398,
      "median_luminance": 82.854,
      "dark_pixel_ratio": 0.219686,
      "similarity_to_selected_frame": 0.03328,
      "duplicate_of_source_filename": "frame_0070.jpg"
    },
    {
      "source_filename": "frame_0074.jpg",
      "source_path": "corpus/05_frames/tv_com_1980_46/frame_0074.jpg",
      "timestamp_seconds": 18.25,
      "rejection_reason": "duplicate_frame",
      "mean_luminance": 81.046,
      "median_luminance": 83.797,
      "dark_pixel_ratio": 0.21393,
      "similarity_to_selected_frame": 0.022377,
      "duplicate_of_source_filename": "frame_0073.jpg"
    },
    {
      "source_filename": "frame_0076.jpg",
      "source_path": "corpus/05_frames/tv_com_1980_46/frame_0076.jpg",
      "timestamp_seconds": 18.75,
      "rejection_reason": "duplicate_frame",
      "mean_luminance": 82.381,
      "median_luminance": 85.964,
      "dark_pixel_ratio": 0.211512,
      "similarity_to_selected_frame": 0.017318,
      "duplicate_of_source_filename": "frame_0075.jpg"
    },
    {
      "source_filename": "frame_0077.jpg",
      "source_path": "corpus/05_frames/tv_com_1980_46/frame_0077.jpg",
      "timestamp_seconds": 19.0,
      "rejection_reason": "duplicate_frame",
      "mean_luminance": 81.961,
      "median_luminance": 85.828,
      "dark_pixel_ratio": 0.215235,
      "similarity_to_selected_frame": 0.025402,
      "duplicate_of_source_filename": "frame_0075.jpg"
    },
    {
      "source_filename": "frame_0078.jpg",
      "source_path": "corpus/05_frames/tv_com_1980_46/frame_0078.jpg",
      "timestamp_seconds": 19.25,
      "rejection_reason": "duplicate_frame",
      "mean_luminance": 82.636,
      "median_luminance": 86.666,
      "dark_pixel_ratio": 0.202399,
      "similarity_to_selected_frame": 0.030787,
      "duplicate_of_source_filename": "frame_0075.jpg"
    },
    {
      "source_filename": "frame_0079.jpg",
      "source_path": "corpus/05_frames/tv_com_1980_46/frame_0079.jpg",
      "timestamp_seconds": 19.5,
      "rejection_reason": "duplicate_frame",
      "mean_luminance": 84.703,
      "median_luminance": 88.712,
      "dark_pixel_ratio": 0.197259,
      "similarity_to_selected_frame": 0.034092,
      "duplicate_of_source_filename": "frame_0075.jpg"
    },
    {
      "source_filename": "frame_0081.jpg",
      "source_path": "corpus/05_frames/tv_com_1980_46/frame_0081.jpg",
      "timestamp_seconds": 20.0,
      "rejection_reason": "duplicate_frame",
      "mean_luminance": 85.253,
      "median_luminance": 89.811,
      "dark_pixel_ratio": 0.193741,
      "similarity_to_selected_frame": 0.010283,
      "duplicate_of_source_filename": "frame_0080.jpg"
    },
    {
      "source_filename": "frame_0082.jpg",
      "source_path": "corpus/05_frames/tv_com_1980_46/frame_0082.jpg",
      "timestamp_seconds": 20.25,
      "rejection_reason": "duplicate_frame",
      "mean_luminance": 85.456,
      "median_luminance": 89.918,
      "dark_pixel_ratio": 0.1935,
      "similarity_to_selected_frame": 0.017582,
      "duplicate_of_source_filename": "frame_0080.jpg"
    },
    {
      "source_filename": "frame_0083.jpg",
      "source_path": "corpus/05_frames/tv_com_1980_46/frame_0083.jpg",
      "timestamp_seconds": 20.5,
      "rejection_reason": "duplicate_frame",
      "mean_luminance": 85.17,
      "median_luminance": 89.426,
      "dark_pixel_ratio": 0.194985,
      "similarity_to_selected_frame": 0.019045,
      "duplicate_of_source_filename": "frame_0080.jpg"
    },
    {
      "source_filename": "frame_0084.jpg",
      "source_path": "corpus/05_frames/tv_com_1980_46/frame_0084.jpg",
      "timestamp_seconds": 20.75,
      "rejection_reason": "duplicate_frame",
      "mean_luminance": 84.594,
      "median_luminance": 89.055,
      "dark_pixel_ratio": 0.201346,
      "similarity_to_selected_frame": 0.02451,
      "duplicate_of_source_filename": "frame_0080.jpg"
    },
    {
      "source_filename": "frame_0092.jpg",
      "source_path": "corpus/05_frames/tv_com_1980_46/frame_0092.jpg",
      "timestamp_seconds": 22.75,
      "rejection_reason": "dark_frame",
      "mean_luminance": 0.591,
      "median_luminance": 0.0,
      "dark_pixel_ratio": 0.997421,
      "similarity_to_selected_frame": null,
      "duplicate_of_source_filename": null
    },
    {
      "source_filename": "frame_0093.jpg",
      "source_path": "corpus/05_frames/tv_com_1980_46/frame_0093.jpg",
      "timestamp_seconds": 23.0,
      "rejection_reason": "dark_frame",
      "mean_luminance": 2.348,
      "median_luminance": 0.0,
      "dark_pixel_ratio": 0.982411,
      "similarity_to_selected_frame": null,
      "duplicate_of_source_filename": null
    },
    {
      "source_filename": "frame_0094.jpg",
      "source_path": "corpus/05_frames/tv_com_1980_46/frame_0094.jpg",
      "timestamp_seconds": 23.25,
      "rejection_reason": "dark_frame",
      "mean_luminance": 6.234,
      "median_luminance": 0.0,
      "dark_pixel_ratio": 0.953613,
      "similarity_to_selected_frame": null,
      "duplicate_of_source_filename": null
    },
    {
      "source_filename": "frame_0095.jpg",
      "source_path": "corpus/05_frames/tv_com_1980_46/frame_0095.jpg",
      "timestamp_seconds": 23.5,
      "rejection_reason": "dark_frame",
      "mean_luminance": 11.506,
      "median_luminance": 0.0,
      "dark_pixel_ratio": 0.915794,
      "similarity_to_selected_frame": null,
      "duplicate_of_source_filename": null
    },
    {
      "source_filename": "frame_0096.jpg",
      "source_path": "corpus/05_frames/tv_com_1980_46/frame_0096.jpg",
      "timestamp_seconds": 23.75,
      "rejection_reason": "dark_frame",
      "mean_luminance": 13.954,
      "median_luminance": 0.0,
      "dark_pixel_ratio": 0.899575,
      "similarity_to_selected_frame": null,
      "duplicate_of_source_filename": null
    },
    {
      "source_filename": "frame_0097.jpg",
      "source_path": "corpus/05_frames/tv_com_1980_46/frame_0097.jpg",
      "timestamp_seconds": 24.0,
      "rejection_reason": "dark_frame",
      "mean_luminance": 24.524,
      "median_luminance": 0.0,
      "dark_pixel_ratio": 0.819619,
      "similarity_to_selected_frame": null,
      "duplicate_of_source_filename": null
    },
    {
      "source_filename": "frame_0098.jpg",
      "source_path": "corpus/05_frames/tv_com_1980_46/frame_0098.jpg",
      "timestamp_seconds": 24.25,
      "rejection_reason": "dark_frame",
      "mean_luminance": 24.582,
      "median_luminance": 0.0,
      "dark_pixel_ratio": 0.819639,
      "similarity_to_selected_frame": null,
      "duplicate_of_source_filename": null
    },
    {
      "source_filename": "frame_0099.jpg",
      "source_path": "corpus/05_frames/tv_com_1980_46/frame_0099.jpg",
      "timestamp_seconds": 24.5,
      "rejection_reason": "dark_frame",
      "mean_luminance": 24.538,
      "median_luminance": 0.0,
      "dark_pixel_ratio": 0.819438,
      "similarity_to_selected_frame": null,
      "duplicate_of_source_filename": null
    },
    {
      "source_filename": "frame_0100.jpg",
      "source_path": "corpus/05_frames/tv_com_1980_46/frame_0100.jpg",
      "timestamp_seconds": 24.75,
      "rejection_reason": "dark_frame",
      "mean_luminance": 24.591,
      "median_luminance": 0.0,
      "dark_pixel_ratio": 0.819426,
      "similarity_to_selected_frame": null,
      "duplicate_of_source_filename": null
    },
    {
      "source_filename": "frame_0101.jpg",
      "source_path": "corpus/05_frames/tv_com_1980_46/frame_0101.jpg",
      "timestamp_seconds": 25.0,
      "rejection_reason": "dark_frame",
      "mean_luminance": 24.567,
      "median_luminance": 0.0,
      "dark_pixel_ratio": 0.819512,
      "similarity_to_selected_frame": null,
      "duplicate_of_source_filename": null
    },
    {
      "source_filename": "frame_0102.jpg",
      "source_path": "corpus/05_frames/tv_com_1980_46/frame_0102.jpg",
      "timestamp_seconds": 25.25,
      "rejection_reason": "dark_frame",
      "mean_luminance": 24.486,
      "median_luminance": 0.0,
      "dark_pixel_ratio": 0.819619,
      "similarity_to_selected_frame": null,
      "duplicate_of_source_filename": null
    },
    {
      "source_filename": "frame_0103.jpg",
      "source_path": "corpus/05_frames/tv_com_1980_46/frame_0103.jpg",
      "timestamp_seconds": 25.5,
      "rejection_reason": "dark_frame",
      "mean_luminance": 24.52,
      "median_luminance": 0.0,
      "dark_pixel_ratio": 0.819628,
      "similarity_to_selected_frame": null,
      "duplicate_of_source_filename": null
    },
    {
      "source_filename": "frame_0104.jpg",
      "source_path": "corpus/05_frames/tv_com_1980_46/frame_0104.jpg",
      "timestamp_seconds": 25.75,
      "rejection_reason": "dark_frame",
      "mean_luminance": 24.593,
      "median_luminance": 0.0,
      "dark_pixel_ratio": 0.819429,
      "similarity_to_selected_frame": null,
      "duplicate_of_source_filename": null
    },
    {
      "source_filename": "frame_0105.jpg",
      "source_path": "corpus/05_frames/tv_com_1980_46/frame_0105.jpg",
      "timestamp_seconds": 26.0,
      "rejection_reason": "dark_frame",
      "mean_luminance": 24.621,
      "median_luminance": 0.0,
      "dark_pixel_ratio": 0.819313,
      "similarity_to_selected_frame": null,
      "duplicate_of_source_filename": null
    },
    {
      "source_filename": "frame_0106.jpg",
      "source_path": "corpus/05_frames/tv_com_1980_46/frame_0106.jpg",
      "timestamp_seconds": 26.25,
      "rejection_reason": "dark_frame",
      "mean_luminance": 24.528,
      "median_luminance": 0.0,
      "dark_pixel_ratio": 0.819797,
      "similarity_to_selected_frame": null,
      "duplicate_of_source_filename": null
    },
    {
      "source_filename": "frame_0107.jpg",
      "source_path": "corpus/05_frames/tv_com_1980_46/frame_0107.jpg",
      "timestamp_seconds": 26.5,
      "rejection_reason": "dark_frame",
      "mean_luminance": 24.532,
      "median_luminance": 0.0,
      "dark_pixel_ratio": 0.819695,
      "similarity_to_selected_frame": null,
      "duplicate_of_source_filename": null
    },
    {
      "source_filename": "frame_0108.jpg",
      "source_path": "corpus/05_frames/tv_com_1980_46/frame_0108.jpg",
      "timestamp_seconds": 26.75,
      "rejection_reason": "dark_frame",
      "mean_luminance": 24.54,
      "median_luminance": 0.0,
      "dark_pixel_ratio": 0.819553,
      "similarity_to_selected_frame": null,
      "duplicate_of_source_filename": null
    },
    {
      "source_filename": "frame_0109.jpg",
      "source_path": "corpus/05_frames/tv_com_1980_46/frame_0109.jpg",
      "timestamp_seconds": 27.0,
      "rejection_reason": "dark_frame",
      "mean_luminance": 24.606,
      "median_luminance": 0.0,
      "dark_pixel_ratio": 0.819539,
      "similarity_to_selected_frame": null,
      "duplicate_of_source_filename": null
    },
    {
      "source_filename": "frame_0110.jpg",
      "source_path": "corpus/05_frames/tv_com_1980_46/frame_0110.jpg",
      "timestamp_seconds": 27.25,
      "rejection_reason": "dark_frame",
      "mean_luminance": 24.508,
      "median_luminance": 0.0,
      "dark_pixel_ratio": 0.819668,
      "similarity_to_selected_frame": null,
      "duplicate_of_source_filename": null
    },
    {
      "source_filename": "frame_0111.jpg",
      "source_path": "corpus/05_frames/tv_com_1980_46/frame_0111.jpg",
      "timestamp_seconds": 27.5,
      "rejection_reason": "dark_frame",
      "mean_luminance": 24.673,
      "median_luminance": 0.0,
      "dark_pixel_ratio": 0.8193,
      "similarity_to_selected_frame": null,
      "duplicate_of_source_filename": null
    },
    {
      "source_filename": "frame_0112.jpg",
      "source_path": "corpus/05_frames/tv_com_1980_46/frame_0112.jpg",
      "timestamp_seconds": 27.75,
      "rejection_reason": "dark_frame",
      "mean_luminance": 24.707,
      "median_luminance": 0.0,
      "dark_pixel_ratio": 0.819268,
      "similarity_to_selected_frame": null,
      "duplicate_of_source_filename": null
    },
    {
      "source_filename": "frame_0113.jpg",
      "source_path": "corpus/05_frames/tv_com_1980_46/frame_0113.jpg",
      "timestamp_seconds": 28.0,
      "rejection_reason": "dark_frame",
      "mean_luminance": 24.677,
      "median_luminance": 0.0,
      "dark_pixel_ratio": 0.81944,
      "similarity_to_selected_frame": null,
      "duplicate_of_source_filename": null
    },
    {
      "source_filename": "frame_0114.jpg",
      "source_path": "corpus/05_frames/tv_com_1980_46/frame_0114.jpg",
      "timestamp_seconds": 28.25,
      "rejection_reason": "dark_frame",
      "mean_luminance": 24.638,
      "median_luminance": 0.0,
      "dark_pixel_ratio": 0.819361,
      "similarity_to_selected_frame": null,
      "duplicate_of_source_filename": null
    },
    {
      "source_filename": "frame_0115.jpg",
      "source_path": "corpus/05_frames/tv_com_1980_46/frame_0115.jpg",
      "timestamp_seconds": 28.5,
      "rejection_reason": "dark_frame",
      "mean_luminance": 24.716,
      "median_luminance": 0.0,
      "dark_pixel_ratio": 0.819198,
      "similarity_to_selected_frame": null,
      "duplicate_of_source_filename": null
    },
    {
      "source_filename": "frame_0116.jpg",
      "source_path": "corpus/05_frames/tv_com_1980_46/frame_0116.jpg",
      "timestamp_seconds": 28.75,
      "rejection_reason": "dark_frame",
      "mean_luminance": 24.647,
      "median_luminance": 0.0,
      "dark_pixel_ratio": 0.819689,
      "similarity_to_selected_frame": null,
      "duplicate_of_source_filename": null
    },
    {
      "source_filename": "frame_0117.jpg",
      "source_path": "corpus/05_frames/tv_com_1980_46/frame_0117.jpg",
      "timestamp_seconds": 29.023,
      "rejection_reason": "dark_frame",
      "mean_luminance": 24.69,
      "median_luminance": 0.0,
      "dark_pixel_ratio": 0.81932,
      "similarity_to_selected_frame": null,
      "duplicate_of_source_filename": null
    }
  ],
  "created_at": "2026-06-18T22:57:27Z",
  "error": null
}